volatility_targeting/__init__.py
volatility_targeting/core.py
volatility_targeting-0.1.0.dist-info/METADATA
volatility_targeting-0.1.0.dist-info/WHEEL
volatility_targeting-0.1.0.dist-info/top_level.txt
volatility_targeting-0.1.0.dist-info/RECORD
