Metadata-Version: 2.4
Name: volatility-targeting
Version: 0.1.0
Summary: Volatility targeting for equal risk portfolio weighting.
Home-page: https://github.com/yourusername/volatility-targeting
Author: Your Name
Author-email: your@email.com
Classifier: Programming Language :: Python :: 3
Classifier: Operating System :: OS Independent
Requires-Python: >=3.7
Requires-Dist: numpy
Requires-Dist: pandas
Dynamic: author
Dynamic: author-email
Dynamic: classifier
Dynamic: description
Dynamic: description-content-type
Dynamic: home-page
Dynamic: requires-dist
Dynamic: requires-python
Dynamic: summary
